swf_typed/__init__.py
swf_typed/_activities.py
swf_typed/_common.py
swf_typed/_decisions.py
swf_typed/_domains.py
swf_typed/_exceptions.py
swf_typed/_executions.py
swf_typed/_history.py
swf_typed/_state.py
swf_typed/_tasks.py
swf_typed/_workflows.py
swf_typed-1.1.2.dist-info/LICENSE
swf_typed-1.1.2.dist-info/METADATA
swf_typed-1.1.2.dist-info/WHEEL
swf_typed-1.1.2.dist-info/top_level.txt
swf_typed-1.1.2.dist-info/RECORD
