Metadata-Version: 2.1
Name: swf-typed
Version: 1.1.2
Summary: Typed Python interface to AWS Simple Workflow service
Home-page: https://github.com/EpicWink/python-swf-typed
Author: Laurie
Author-email: laurie_opperman@hotmail.com
License: "MIT"
Project-URL: Documentation, https://python-swf-typed.readthedocs.io/
Project-URL: Source, https://github.com/EpicWink/python-swf-typed
Project-URL: Tracker, https://github.com/EpicWink/python-swf-typed/issues
Project-URL: Changelog, https://github.com/EpicWink/python-swf-typed/releases
Keywords: swf,typed
Requires-Python: ~=3.7
License-File: LICENSE
Requires-Dist: boto3 ~=1.18
